{
	"parent": "block/block",
	"textures": {
		"0": "minecraft:block/glass",
		"1": "uprightss:block/glass_upright_slab_left_right",
		"particle": "minecraft:block/glass"
	},
	"elements": [
		{
			"from": [0, 0, 0],
			"to": [8, 16, 16],
			"faces": {
				"north": {"uv": [0, 0, 8, 16], "texture": "#1", "cullface": "north"},
				"east": {"uv": [0, 0, 16, 16], "texture": "#0"},
				"south": {"uv": [0, 0, 8, 16], "texture": "#1", "cullface": "south"},
				"west": {"uv": [0, 0, 16, 16], "texture": "#0", "cullface": "west"},
				"up": {"uv": [0, 0, 8, 16], "texture": "#1", "cullface": "up"},
				"down": {"uv": [0, 0, 8, 16], "texture": "#1", "cullface": "down"}
			}
		}
	]
}